webzio
